flwr/__init__.py
flwr/app/__init__.py
flwr/app/error.py
flwr/app/exception.py
flwr/app/metadata.py
flwr/cli/__init__.py
flwr/cli/app.py
flwr/cli/app_cmd/__init__.py
flwr/cli/app_cmd/publish.py
flwr/cli/app_cmd/review.py
flwr/cli/auth_plugin/__init__.py
flwr/cli/auth_plugin/auth_plugin.py
flwr/cli/auth_plugin/noop_auth_plugin.py
flwr/cli/auth_plugin/oidc_cli_plugin.py
flwr/cli/build.py
flwr/cli/cli_account_auth_interceptor.py
flwr/cli/config_utils.py
flwr/cli/constant.py
flwr/cli/example.py
flwr/cli/federation/__init__.py
flwr/cli/federation/ls.py
flwr/cli/federation/show.py
flwr/cli/install.py
flwr/cli/log.py
flwr/cli/login/__init__.py
flwr/cli/login/login.py
flwr/cli/ls.py
flwr/cli/new/__init__.py
flwr/cli/new/new.py
flwr/cli/pull.py
flwr/cli/run/__init__.py
flwr/cli/run/run.py
flwr/cli/run_utils.py
flwr/cli/stop.py
flwr/cli/supernode/__init__.py
flwr/cli/supernode/ls.py
flwr/cli/supernode/register.py
flwr/cli/supernode/unregister.py
flwr/cli/utils.py
flwr/client/__init__.py
flwr/client/client.py
flwr/client/dpfedavg_numpy_client.py
flwr/client/grpc_adapter_client/__init__.py
flwr/client/grpc_adapter_client/connection.py
flwr/client/grpc_rere_client/__init__.py
flwr/client/grpc_rere_client/connection.py
flwr/client/grpc_rere_client/grpc_adapter.py
flwr/client/grpc_rere_client/node_auth_client_interceptor.py
flwr/client/message_handler/__init__.py
flwr/client/message_handler/message_handler.py
flwr/client/mod/__init__.py
flwr/client/mod/centraldp_mods.py
flwr/client/mod/comms_mods.py
flwr/client/mod/localdp_mod.py
flwr/client/mod/secure_aggregation/__init__.py
flwr/client/mod/secure_aggregation/secagg_mod.py
flwr/client/mod/secure_aggregation/secaggplus_mod.py
flwr/client/mod/utils.py
flwr/client/numpy_client.py
flwr/client/rest_client/__init__.py
flwr/client/rest_client/connection.py
flwr/client/run_info_store.py
flwr/client/typing.py
flwr/clientapp/__init__.py
flwr/clientapp/client_app.py
flwr/clientapp/mod/__init__.py
flwr/clientapp/mod/centraldp_mods.py
flwr-1.25.0.dist-info/METADATA
flwr-1.25.0.dist-info/WHEEL
flwr-1.25.0.dist-info/entry_points.txt
flwr-1.25.0.dist-info/RECORD
