Metadata-Version: 2.3
Name: flwr
Version: 1.25.0
Summary: Flower: A Friendly Federated AI Framework
License: Apache-2.0
Keywords: Artificial Intelligence,Federated AI,Federated Analytics,Federated Evaluation,Federated Learning,Flower,Machine Learning
Author: The Flower Authors
Author-email: hello@flower.ai
Requires-Python: >=3.10,<4.0
Classifier: Development Status :: 5 - Production/Stable
Classifier: Intended Audience :: Developers
Classifier: Intended Audience :: Science/Research
Classifier: License :: OSI Approved :: Apache Software License
Classifier: Operating System :: MacOS :: MacOS X
Classifier: Operating System :: POSIX :: Linux
Classifier: Programming Language :: Python
Classifier: Programming Language :: Python :: 3
Classifier: Programming Language :: Python :: 3.10
Classifier: Programming Language :: Python :: 3.11
Classifier: Programming Language :: Python :: 3.12
Classifier: Programming Language :: Python :: 3.13
Classifier: Programming Language :: Python :: 3 :: Only
Classifier: Programming Language :: Python :: Implementation :: CPython
Classifier: Topic :: Scientific/Engineering
Classifier: Topic :: Scientific/Engineering :: Artificial Intelligence
Classifier: Topic :: Scientific/Engineering :: Mathematics
Classifier: Topic :: Software Development
Classifier: Topic :: Software Development :: Libraries
Classifier: Topic :: Software Development :: Libraries :: Python Modules
Classifier: Typing :: Typed
Provides-Extra: rest
Provides-Extra: simulation
Requires-Dist: click (<8.2.0)
Requires-Dist: cryptography (>=44.0.1,<45.0.0)
Requires-Dist: grpcio (>=1.70.0,<2.0.0)
Requires-Dist: grpcio-health-checking (>=1.70.0,<2.0.0)
Requires-Dist: iterators (>=0.0.2,<0.0.3)
Requires-Dist: numpy (>=1.26.0,<3.0.0)
Requires-Dist: pathspec (>=0.12.1,<0.13.0)
Requires-Dist: protobuf (>=5.28.0,<7.0.0)
Requires-Dist: pycryptodome (>=3.18.0,<4.0.0)
Requires-Dist: pyyaml (>=6.0.2,<7.0.0)
Requires-Dist: ray (==2.51.1) ; (python_version >= "3.10" and python_version < "3.13") and (extra == "simulation")
Requires-Dist: ray (==2.51.1) ; (sys_platform != "win32" and python_version == "3.13") and (extra == "simulation")
Requires-Dist: requests (>=2.31.0,<3.0.0)
Requires-Dist: rich (>=13.5.0,<14.0.0)
Requires-Dist: starlette (>=0.45.2,<0.46.0) ; extra == "rest"
Requires-Dist: tomli (>=2.0.1,<3.0.0)
Requires-Dist: tomli-w (>=1.0.0,<2.0.0)
Requires-Dist: typer (>=0.12.5,<0.21.0)
Requires-Dist: uvicorn[standard] (>=0.34.0,<0.35.0) ; extra == "rest"
Project-URL: Documentation, https://flower.ai
Project-URL: Homepage, https://flower.ai
Project-URL: Repository, https://github.com/adap/flower
